Metadata-Version: 1.0
Name: gpsdio
Version: 0.0.7
Summary: A general purpose AIS I/O library using the GPSd AIVDM schema.
Home-page: https://github.com/SkyTruth/gpsdio
Author: Egil Moeller, Kevin Wurster
Author-email: egil@skytruth.org, kevin@skytruth.org
License: Apache 2.0
Keywords: GPSd AIVDM AIS I/O
Platform: UNKNOWN
